nameco/__init__.py
nameco/run_nameco.py
nameco-1.2.1.dist-info/licenses/LICENSE
nameco-1.2.1.dist-info/METADATA
nameco-1.2.1.dist-info/WHEEL
nameco-1.2.1.dist-info/entry_points.txt
nameco-1.2.1.dist-info/top_level.txt
nameco-1.2.1.dist-info/RECORD
