Metadata-Version: 2.4
Name: nameco
Version: 1.2.1
Summary: Pipeline for the Nanopore 16S long read clustering and taxonomy classification
Author-email: Timur Yergaliyev <timyerg@gmail.com>
Project-URL: Homepage, https://github.com/timyerg/NaMeco
Project-URL: Issues, https://github.com/timyerg/NaMeco/issues
Classifier: Programming Language :: Python :: 3
Classifier: License :: OSI Approved :: Apache Software License
Classifier: Operating System :: POSIX :: Linux
Requires-Python: >=3.8
License-File: LICENSE
Dynamic: license-file
